nestml_server/__init__.py
nestml_server/main.py
nestml_server-1.0.0b3.data/scripts/nestml-server
nestml_server-1.0.0b3.dist-info/LICENSE
nestml_server-1.0.0b3.dist-info/METADATA
nestml_server-1.0.0b3.dist-info/WHEEL
nestml_server-1.0.0b3.dist-info/top_level.txt
nestml_server-1.0.0b3.dist-info/RECORD
