Metadata-Version: 2.1
Name: nestml-server
Version: 1.0.0b3
Summary: A server instance for NESTML
Author-email: Sebastian Spreizer <spreizer@web.de>
License: MIT License
Project-URL: repository, https://github.com/babsey/nestml-server
Project-URL: documentation, https://nestml.readthedocs.io
Classifier: Development Status :: 4 - Beta
Classifier: Intended Audience :: End Users/Desktop
Classifier: Intended Audience :: Science/Research
Classifier: Topic :: Education
Classifier: License :: OSI Approved :: MIT License
Classifier: Programming Language :: Python :: 3
Requires-Python: >=3.8
License-File: LICENSE
Requires-Dist: flask
Requires-Dist: flask-cors
Requires-Dist: gunicorn
Requires-Dist: nestml >=7.0
